pretix_automated_orders/__init__.py
pretix_automated_orders/apps.py
pretix_automated_orders/forms.py
pretix_automated_orders/signals.py
pretix_automated_orders/tasks.py
pretix_automated_orders/urls.py
pretix_automated_orders/views.py
pretix_automated_orders/locale/.DS_Store
pretix_automated_orders/locale/de/.DS_Store
pretix_automated_orders/locale/de/LC_MESSAGES/django.mo
pretix_automated_orders/locale/de/LC_MESSAGES/django.po
pretix_automated_orders/locale/de_Informal/.gitkeep
pretix_automated_orders/locale/de_Informal/LC_MESSAGES/django.mo
pretix_automated_orders/locale/de_Informal/LC_MESSAGES/django.po
pretix_automated_orders/locale/pt/LC_MESSAGES/django.mo
pretix_automated_orders/locale/pt/LC_MESSAGES/django.po
pretix_automated_orders/static/automated_orders/.gitkeep
pretix_automated_orders/templates/automated_orders/.gitkeep
pretix_automated_orders/templates/automated_orders/index.html
pretix_automated_orders-1.1.7.dist-info/LICENSE
pretix_automated_orders-1.1.7.dist-info/METADATA
pretix_automated_orders-1.1.7.dist-info/WHEEL
pretix_automated_orders-1.1.7.dist-info/entry_points.txt
pretix_automated_orders-1.1.7.dist-info/top_level.txt
pretix_automated_orders-1.1.7.dist-info/RECORD
